cjy_wfy9/__init__.py
cjy_wfy9/background.jpg
cjy_wfy9/crash.wav
cjy_wfy9/font.ttf
cjy_wfy9/kaiti.ttf
cjy_wfy9/main.py
cjy_wfy9/racecar.jpg
cjy_wfy9/racestart.wav
cjy_wfy9/tiantiande.wav
cjy_wfy9/photos/1.jpg
cjy_wfy9/photos/10.jpg
cjy_wfy9/photos/11.jpg
cjy_wfy9/photos/12.jpg
cjy_wfy9/photos/13.jpg
cjy_wfy9/photos/14.jpg
cjy_wfy9/photos/15.jpg
cjy_wfy9/photos/2.jpg
cjy_wfy9/photos/3.jpg
cjy_wfy9/photos/4.jpg
cjy_wfy9/photos/5.jpg
cjy_wfy9/photos/6.jpg
cjy_wfy9/photos/7.jpg
cjy_wfy9/photos/70.jpg
cjy_wfy9/photos/8.jpg
cjy_wfy9/photos/9.jpg
cjy_wfy9-0.0.1.dist-info/LICENSE
cjy_wfy9-0.0.1.dist-info/METADATA
cjy_wfy9-0.0.1.dist-info/WHEEL
cjy_wfy9-0.0.1.dist-info/top_level.txt
cjy_wfy9-0.0.1.dist-info/RECORD
